apiwrappers/AMP120.py
apiwrappers/CAM600.py
apiwrappers/FSC640.py
apiwrappers/IP5100.py
apiwrappers/MS0402_N011.py
apiwrappers/MV0401_H2H4K60.py
apiwrappers/MV0401_H2H4K60_001.py
apiwrappers/MV0401_H2H4K60_TCP.py
apiwrappers/MX0404_N301.py
apiwrappers/SC009.py
apiwrappers/SC010.py
apiwrappers/SW0401_N081_000.py
apiwrappers/__init__.py
apiwrappers/_version.py
apiwrappers/find_aspeed_devices.py
proitav_api_wrappers-1.3.3.dist-info/LICENSE
proitav_api_wrappers-1.3.3.dist-info/METADATA
proitav_api_wrappers-1.3.3.dist-info/WHEEL
proitav_api_wrappers-1.3.3.dist-info/top_level.txt
proitav_api_wrappers-1.3.3.dist-info/RECORD
