Metadata-Version: 2.1
Name: proitav-api-wrappers
Version: 1.3.3
Summary: API Wrapper for ProITAV Products
Home-page: https://github.com/jfaulk1434/proitav-api-wrappers
Author: Justin Faulk
Author-email: jfaulk@proitav.us
Classifier: Development Status :: 3 - Alpha
Classifier: Intended Audience :: Developers
Classifier: License :: OSI Approved :: MIT License
Classifier: Programming Language :: Python :: 3
Classifier: Programming Language :: Python :: 3.6
Classifier: Programming Language :: Python :: 3.7
Classifier: Programming Language :: Python :: 3.8
Classifier: Programming Language :: Python :: 3.9
Requires-Python: >=3.6
License-File: LICENSE
Requires-Dist: pyserial
Requires-Dist: pexpect
Requires-Dist: telnetlib3
